.gitignore
README.txt
releaseNewVersion.py
setup.py
RO.egg-info/PKG-INFO
RO.egg-info/SOURCES.txt
RO.egg-info/dependency_links.txt
RO.egg-info/not-zip-safe
RO.egg-info/top_level.txt
docs/Install.html
docs/License.txt
docs/Overview.html
docs/VersionHistory.html
python/RO/AddCallback.py
python/RO/BitDescr.py
python/RO/CanvasUtil.py
python/RO/CnvUtil.py
python/RO/Constants.py
python/RO/CoordSys.py
python/RO/DS9.py
python/RO/InputCont.py
python/RO/KeyDispatcher.py
python/RO/KeyVariable.py
python/RO/LangUtil.py
python/RO/MathUtil.py
python/RO/PVT.py
python/RO/PhysConst.py
python/RO/SQLUtil.py
python/RO/ScriptRunner.py
python/RO/SeqUtil.py
python/RO/StringUtil.py
python/RO/SysConst.py
python/RO/TkUtil.py
python/RO/Version.py
python/RO/__init__.py
python/RO/procFiles.py
python/RO/Alg/GenericCallback.py
python/RO/Alg/IDGen.py
python/RO/Alg/ListPlus.py
python/RO/Alg/MatchList.py
python/RO/Alg/MultiDict.py
python/RO/Alg/MultiListIter.py
python/RO/Alg/OrderedDict.py
python/RO/Alg/RandomWalk.py
python/RO/Alg/SavedDict.py
python/RO/Alg/__init__.py
python/RO/Astro/ImageWindow.py
python/RO/Astro/__init__.py
python/RO/Astro/runTests.py
python/RO/Astro/Cnv/AppGeoData.py
python/RO/Astro/Cnv/AzAltFromHADec.py
python/RO/Astro/Cnv/CoordConv.py
python/RO/Astro/Cnv/FK4FromICRS.py
python/RO/Astro/Cnv/FK5Prec.py
python/RO/Astro/Cnv/GalFromICRS.py
python/RO/Astro/Cnv/GeoFromICRS.py
python/RO/Astro/Cnv/GeoFromTopo.py
python/RO/Astro/Cnv/HADecFromAzAlt.py
python/RO/Astro/Cnv/ICRSFromFK4.py
python/RO/Astro/Cnv/ICRSFromFixedFK4.py
python/RO/Astro/Cnv/ICRSFromGal.py
python/RO/Astro/Cnv/ICRSFromGeo.py
python/RO/Astro/Cnv/ObsFromTopo.py
python/RO/Astro/Cnv/ObserverData.py
python/RO/Astro/Cnv/TopoFromGeo.py
python/RO/Astro/Cnv/TopoFromGeoSimple.py
python/RO/Astro/Cnv/TopoFromObs.py
python/RO/Astro/Cnv/__init__.py
python/RO/Astro/Sph/Airmass.py
python/RO/Astro/Sph/AngSep.py
python/RO/Astro/Sph/AngSideAng.py
python/RO/Astro/Sph/AzAltFromHADec.py
python/RO/Astro/Sph/CCFromSC.py
python/RO/Astro/Sph/CCFromSCPV.py
python/RO/Astro/Sph/CCFromSCPVOff.py
python/RO/Astro/Sph/Const.py
python/RO/Astro/Sph/CoordConv.py
