Metadata-Version: 1.1
Name: RO
Version: 3.6.5
Summary: Collection of utilities including general algorithms, astronomical transformations and Tkinter widgets
Home-page: http://www.astro.washington.edu/rowen/
Author: Russell Owen
Author-email: rowen@uw.edu
License: MIT except RO.Astro which has more restrictions for commercial use
Platform: MacOS X
Platform: unix
Platform: Windows
Classifier: Development Status :: 5 - Production/Stable
Classifier: Programming Language :: Python :: 2.6
Classifier: Programming Language :: Python :: 2.7
Classifier: Topic :: Software Development :: Libraries :: Python Modules
